pointercratepy/__init__.py
pointercratepy-1.1.0.dist-info/LICENSE.txt
pointercratepy-1.1.0.dist-info/METADATA
pointercratepy-1.1.0.dist-info/WHEEL
pointercratepy-1.1.0.dist-info/top_level.txt
pointercratepy-1.1.0.dist-info/RECORD
