Metadata-Version: 2.1
Name: pointercratepy
Version: 1.1.0
Summary: API wrapper for Pointercrate.
Home-page: https://github.com/bretheskevin/pointercrate.py
Author: Kévin BRETHES
Author-email: bretheskevin@gmail.com
Classifier: Programming Language :: Python :: 3
Classifier: License :: OSI Approved :: MIT License
Classifier: Operating System :: OS Independent
Requires-Python: >=3.7
License-File: LICENSE.txt
